isitsecure/__init__.py
isitsecure/breach_checker.py
isitsecure/cli.py
isitsecure/password_analyzer.py
isitsecure/password_scanner.py
isitsecure/report_generator.py
isitsecure-1.0.0.dist-info/licenses/LICENSE.txt
isitsecure-1.0.0.dist-info/METADATA
isitsecure-1.0.0.dist-info/WHEEL
isitsecure-1.0.0.dist-info/entry_points.txt
isitsecure-1.0.0.dist-info/top_level.txt
isitsecure-1.0.0.dist-info/RECORD
