Metadata-Version: 2.4
Name: isitsecure
Version: 1.0.0
Summary: A comprehensive password security scanner that analyzes strength and checks breach exposure
Home-page: https://github.com/chrismat-05/IsItSecure
Author: Chris Mathew Aje
Author-email: Chris Mathew Aje <chrismaje63@gmail.com>
License: MIT
Project-URL: Homepage, https://github.com/chrismat-05/IsItSecure
Project-URL: Bug Reports, https://github.com/chrismat-05/IsItSecure/issues
Project-URL: Source, https://github.com/chrismat-05/IsItSecure
Keywords: password,security,breach,scanner,cybersecurity,privacy
Classifier: Development Status :: 4 - Beta
Classifier: Intended Audience :: Developers
Classifier: Intended Audience :: System Administrators
Classifier: License :: OSI Approved :: MIT License
Classifier: Operating System :: OS Independent
Classifier: Programming Language :: Python :: 3
Classifier: Programming Language :: Python :: 3.8
Classifier: Programming Language :: Python :: 3.9
Classifier: Programming Language :: Python :: 3.10
Classifier: Programming Language :: Python :: 3.11
Classifier: Programming Language :: Python :: 3.12
Classifier: Topic :: Security
Classifier: Topic :: Software Development :: Libraries :: Python Modules
Classifier: Topic :: System :: Systems Administration
Requires-Python: >=3.8
License-File: LICENSE.txt
Requires-Dist: requests>=2.28.0
Requires-Dist: colorama>=0.4.6
Requires-Dist: tabulate>=0.9.0
Requires-Dist: tqdm>=4.64.0
Dynamic: author
Dynamic: home-page
Dynamic: license-file
Dynamic: requires-python
